README.md
setup.cfg
setup.py
udo/__init__.py
udo/__main__.py
udo/extract_index.py
udo/agent/__init__.py
udo/agent/ddpg_agent.py
udo/agent/sarsa_agent.py
udo/agent/udo_agent.py
udo/agent/udo_simplifed_agent.py
udo/drivers/__init__.py
udo/drivers/abstractdriver.py
udo/drivers/mysqldriver.py
udo/drivers/postgresdriver.py
udo/mcts/__init__.py
udo/mcts/exp3_node.py
udo/mcts/mcts_node.py
udo/mcts/uct_node.py
udo/optimizer/__init__.py
udo/optimizer/order_optimizer.py
udo/udo-optimization/__init__.py
udo/udo-optimization/setup.py
udo/udo-optimization/udo_optimization/__init__.py
udo/udo-optimization/udo_optimization/envs/__init__.py
udo/udo-optimization/udo_optimization/envs/udo_env.py
udo_db.egg-info/PKG-INFO
udo_db.egg-info/SOURCES.txt
udo_db.egg-info/dependency_links.txt
udo_db.egg-info/requires.txt
udo_db.egg-info/top_level.txt