Metadata-Version: 1.1
Name: udo-db
Version: 0.20
Summary: a universal optimizer for database system
Home-page: https://ovss.github.io/UDO/
Author: Junxiong Wang
Author-email: chuangzhetianxia@gmail.coma
License: MIT
Download-URL: https://github.com/OVSS/UDO/archive/refs/tags/0.01.tar.gz
Keywords: Database Optimization,OLAP,Index selection,System parameters
Platform: UNKNOWN
Classifier: Development Status :: 3 - Alpha
Classifier: Intended Audience :: Developers
Classifier: Topic :: Database
Classifier: License :: OSI Approved :: MIT License
Classifier: Programming Language :: Python :: 3
Classifier: Programming Language :: Python :: 3.4
Classifier: Programming Language :: Python :: 3.5
Classifier: Programming Language :: Python :: 3.6
